recherche_babac2/__init__.py
recherche_babac2/_version.py
recherche_babac2/recherche_babac2.py
Recherche_Babac2-0.2.9.dist-info/LICENSE.md
Recherche_Babac2-0.2.9.dist-info/METADATA
Recherche_Babac2-0.2.9.dist-info/WHEEL
Recherche_Babac2-0.2.9.dist-info/entry_points.txt
Recherche_Babac2-0.2.9.dist-info/top_level.txt
Recherche_Babac2-0.2.9.dist-info/RECORD
