Metadata-Version: 2.1
Name: Recherche-Babac2
Version: 0.2.9
Summary: A Python3 module to search the Cycle Babac catalogue and return description, price and availability.
Home-page: http://github.com/normcyr/recherche_babac2
Author: Normand Cyr
Author-email: norm@normandcyr.com
License: GNU GPLv3
Keywords: bicycle babac parts repair diy
Classifier: Development Status :: 3 - Alpha
Classifier: License :: OSI Approved :: GNU General Public License v3 (GPLv3)
Classifier: Programming Language :: Python :: 3
Classifier: Topic :: Office/Business :: Financial
Requires-Python: >=3.5
License-File: LICENSE.md
Requires-Dist: bs4
Requires-Dist: requests
Requires-Dist: lxml
Requires-Dist: pyyaml
